rdlock/__init__.py
rdlock/consts.py
rdlock/mutex.py
rdlock/py.typed
rdlock_py-0.1.0.dist-info/licenses/LICENSE
rdlock_py-0.1.0.dist-info/METADATA
rdlock_py-0.1.0.dist-info/WHEEL
rdlock_py-0.1.0.dist-info/top_level.txt
rdlock_py-0.1.0.dist-info/RECORD
