Metadata-Version: 2.4
Name: rdlock_py
Version: 0.1.0
Summary: A simple distributed lock based on redis.
Author-email: Kevin Chen <1354016594@qq.com>
License-Expression: MIT
Project-URL: Home-page, https://github.com/czf0613/rdlock_py
Keywords: redis,distributed lock,lock
Classifier: Intended Audience :: Developers
Classifier: Operating System :: Microsoft :: Windows
Classifier: Operating System :: MacOS :: MacOS X
Classifier: Operating System :: POSIX :: Linux
Requires-Python: >=3.10
License-File: LICENSE
Requires-Dist: redis>=7.1.0
Requires-Dist: setuptools>=80.9.0
Dynamic: license-file
